[{"line":3,"elements":[{"start_timestamp":"2022-09-25T22:29:51.775Z","before":[{"result":{"duration":4852000000,"status":"passed"},"match":{"location":"stepDefinitions.Hooks.OpenBrowser()"}}],"line":4,"name":"user choose language","description":"","id":"user-choose-language;user-choose-language","after":[{"result":{"duration":3195000000,"status":"passed"},"match":{"location":"stepDefinitions.Hooks.QuitDriver()"}}],"type":"scenario","keyword":"Scenario","steps":[{"result":{"duration":72000000,"status":"passed"},"line":5,"name":"user click on language list","match":{"location":"stepDefinitions.D01_HomePage.language_list()"},"keyword":"Given "},{"result":{"duration":653000000,"status":"passed"},"line":6,"name":"user choose the language","match":{"location":"stepDefinitions.D01_HomePage.choose_language()"},"keyword":"Then "}],"tags":[{"name":"@smoke"}]}],"name":"user choose language","description":"","id":"user-choose-language","keyword":"Feature","uri":"file:src/main/resources/features/F01_HomePage.feature","tags":[{"name":"@smoke","type":"Tag","location":{"line":2,"column":1}}]},{"line":2,"elements":[{"start_timestamp":"2022-09-25T22:30:00.586Z","before":[{"result":{"duration":3172000000,"status":"passed"},"match":{"location":"stepDefinitions.Hooks.OpenBrowser()"}}],"line":3,"name":"user search about lesson","description":"","id":"user-search-about-lessons;user-search-about-lesson","after":[{"result":{"duration":2729000000,"status":"passed"},"match":{"location":"stepDefinitions.Hooks.QuitDriver()"}}],"type":"scenario","keyword":"Scenario","steps":[{"result":{"duration":80000000,"status":"passed"},"line":4,"name":"user click on language list","match":{"location":"stepDefinitions.D01_HomePage.language_list()"},"keyword":"Given "},{"result":{"duration":648000000,"status":"passed"},"line":5,"name":"user choose the language","match":{"location":"stepDefinitions.D01_HomePage.choose_language()"},"keyword":"When "},{"result":{"duration":88000000,"status":"passed"},"line":6,"name":"user click on search icon","match":{"location":"stepDefinitions.D02_Search.click_search_icon()"},"keyword":"And "},{"result":{"duration":131000000,"status":"passed"},"line":7,"name":"user write the lesson name in search text box","match":{"location":"stepDefinitions.D02_Search.search_txt()"},"keyword":"And "},{"result":{"duration":621000000,"status":"passed"},"line":8,"name":"user click on search submit","match":{"location":"stepDefinitions.D02_Search.search_submit()"},"keyword":"Then "}],"tags":[{"name":"@smoke"}]}],"name":"user search about lessons","description":"","id":"user-search-about-lessons","keyword":"Feature","uri":"file:src/main/resources/features/F02_Search.feature","tags":[{"name":"@smoke","type":"Tag","location":{"line":1,"column":1}}]},{"line":2,"elements":[{"start_timestamp":"2022-09-25T22:30:08.070Z","before":[{"result":{"duration":3500000000,"status":"passed"},"match":{"location":"stepDefinitions.Hooks.OpenBrowser()"}}],"line":3,"name":"user choose second lesson","description":"","id":"user-choose-second-lesson;user-choose-second-lesson","after":[{"result":{"duration":3251000000,"status":"passed"},"match":{"location":"stepDefinitions.Hooks.QuitDriver()"}}],"type":"scenario","keyword":"Scenario","steps":[{"result":{"duration":64000000,"status":"passed"},"line":4,"name":"user click on language list","match":{"location":"stepDefinitions.D01_HomePage.language_list()"},"keyword":"Given "},{"result":{"duration":1199000000,"status":"passed"},"line":5,"name":"user choose the language","match":{"location":"stepDefinitions.D01_HomePage.choose_language()"},"keyword":"When "},{"result":{"duration":88000000,"status":"passed"},"line":6,"name":"user click on search icon","match":{"location":"stepDefinitions.D02_Search.click_search_icon()"},"keyword":"And "},{"result":{"duration":119000000,"status":"passed"},"line":7,"name":"user write the lesson name in search text box","match":{"location":"stepDefinitions.D02_Search.search_txt()"},"keyword":"And "},{"result":{"duration":1542000000,"status":"passed"},"line":8,"name":"user click on search submit","match":{"location":"stepDefinitions.D02_Search.search_submit()"},"keyword":"And "},{"result":{"duration":2545000000,"status":"passed"},"line":9,"name":"user click on 2nd lesson","match":{"location":"stepDefinitions.D03_SearchResult.second_lesson()"},"keyword":"Then "}],"tags":[{"name":"@smoke"}]}],"name":"user choose second lesson","description":"","id":"user-choose-second-lesson","keyword":"Feature","uri":"file:src/main/resources/features/F03_SearchResult.feature","tags":[{"name":"@smoke","type":"Tag","location":{"line":1,"column":1}}]},{"line":2,"elements":[{"start_timestamp":"2022-09-25T22:30:20.417Z","before":[{"result":{"duration":3117000000,"status":"passed"},"match":{"location":"stepDefinitions.Hooks.OpenBrowser()"}}],"line":3,"name":"user choose second lesson","description":"","id":"user-choose-second-lesson;user-choose-second-lesson","after":[{"result":{"duration":2971000000,"status":"passed"},"match":{"location":"stepDefinitions.Hooks.QuitDriver()"}}],"type":"scenario","keyword":"Scenario","steps":[{"result":{"duration":98000000,"status":"passed"},"line":4,"name":"user click on language list","match":{"location":"stepDefinitions.D01_HomePage.language_list()"},"keyword":"Given "},{"result":{"duration":847000000,"status":"passed"},"line":5,"name":"user choose the language","match":{"location":"stepDefinitions.D01_HomePage.choose_language()"},"keyword":"When "},{"result":{"duration":104000000,"status":"passed"},"line":6,"name":"user click on search icon","match":{"location":"stepDefinitions.D02_Search.click_search_icon()"},"keyword":"And "},{"result":{"duration":125000000,"status":"passed"},"line":7,"name":"user write the lesson name in search text box","match":{"location":"stepDefinitions.D02_Search.search_txt()"},"keyword":"And "},{"result":{"duration":918000000,"status":"passed"},"line":8,"name":"user click on search submit","match":{"location":"stepDefinitions.D02_Search.search_submit()"},"keyword":"And "},{"result":{"duration":2352000000,"status":"passed"},"line":9,"name":"user click on 2nd lesson","match":{"location":"stepDefinitions.D03_SearchResult.second_lesson()"},"keyword":"And "},{"result":{"duration":1205000000,"status":"passed"},"line":10,"name":"user click on worksheet section","match":{"location":"stepDefinitions.D04_SecondLesson.worksheet_section()"},"keyword":"Then "}],"tags":[{"name":"@smoke"}]}],"name":"user choose second lesson","description":"","id":"user-choose-second-lesson","keyword":"Feature","uri":"file:src/main/resources/features/F04_SecondLesson.feature","tags":[{"name":"@smoke","type":"Tag","location":{"line":1,"column":1}}]}]